{
    "swagger": "2.0",
    "info": {
        "contact": {}
    },
    "paths": {
        "/admin/main": {
            "get": {
                "description": "Access to mainadmin page",
                "consumes": [
                    "application/json"
                ],
                "produces": [
                    "application/json"
                ],
                "summary": "MainAdmin",
                "responses": {
                    "200": {
                        "description": "OK",
                        "schema": {
                            "type": "string"
                        }
                    }
                }
            }
        },
        "/cats": {
            "post": {
                "description": "AddCat",
                "consumes": [
                    "application/json"
                ],
                "produces": [
                    "application/json"
                ],
                "summary": "AddCat",
                "parameters": [
                    {
                        "description": "cat",
                        "name": "cat",
                        "in": "body",
                        "required": true,
                        "schema": {
                            "$ref": "#/definitions/handlers.Cat"
                        }
                    }
                ],
                "responses": {
                    "200": {
                        "description": "OK",
                        "schema": {
                            "type": "string"
                        }
                    },
                    "500": {
                        "description": "Internal Server Error",
                        "schema": {
                            "type": "string"
                        }
                    }
                }
            }
        },
        "/cats/{data}": {
            "get": {
                "description": "GetCats",
                "consumes": [
                    "application/json"
                ],
                "produces": [
                    "application/json"
                ],
                "summary": "GetCats",
                "parameters": [
                    {
                        "type": "string",
                        "description": "name",
                        "name": "name",
                        "in": "query",
                        "required": true
                    },
                    {
                        "type": "string",
                        "description": "type",
                        "name": "type",
                        "in": "query",
                        "required": true
                    },
                    {
                        "type": "string",
                        "description": "data",
                        "name": "data",
                        "in": "path",
                        "required": true
                    }
                ],
                "responses": {
                    "200": {
                        "description": "OK",
                        "schema": {
                            "type": "string"
                        }
                    },
                    "500": {
                        "description": "Internal Server Error",
                        "schema": {
                            "type": "string"
                        }
                    }
                }
            }
        },
        "/cookie/main": {
            "get": {
                "description": "Access to MainCookie page",
                "consumes": [
                    "application/json"
                ],
                "produces": [
                    "application/json"
                ],
                "summary": "MainCookie",
                "responses": {
                    "200": {
                        "description": "OK",
                        "schema": {
                            "type": "string"
                        }
                    }
                }
            }
        },
        "/dogs": {
            "post": {
                "description": "AddDog",
                "consumes": [
                    "application/json"
                ],
                "produces": [
                    "application/json"
                ],
                "summary": "AddDog",
                "parameters": [
                    {
                        "description": "dog",
                        "name": "dog",
                        "in": "body",
                        "required": true,
                        "schema": {
                            "$ref": "#/definitions/handlers.Dog"
                        }
                    }
                ],
                "responses": {
                    "200": {
                        "description": "OK",
                        "schema": {
                            "type": "string"
                        }
                    },
                    "500": {
                        "description": "Internal Server Error",
                        "schema": {
                            "type": "string"
                        }
                    }
                }
            }
        },
        "/hamsters": {
            "post": {
                "description": "AddHamster",
                "consumes": [
                    "application/json"
                ],
                "produces": [
                    "application/json"
                ],
                "summary": "AddHamster",
                "parameters": [
                    {
                        "description": "hamster",
                        "name": "hamster",
                        "in": "body",
                        "required": true,
                        "schema": {
                            "$ref": "#/definitions/handlers.Hamster"
                        }
                    }
                ],
                "responses": {
                    "200": {
                        "description": "OK",
                        "schema": {
                            "type": "string"
                        }
                    },
                    "500": {
                        "description": "Internal Server Error",
                        "schema": {
                            "type": "string"
                        }
                    }
                }
            }
        },
        "/hi": {
            "get": {
                "description": "Access to Hi page",
                "consumes": [
                    "application/json"
                ],
                "produces": [
                    "application/json"
                ],
                "summary": "HI",
                "responses": {
                    "200": {
                        "description": "OK",
                        "schema": {
                            "type": "string"
                        }
                    }
                }
            }
        },
        "/jwt/main": {
            "get": {
                "description": "Access to MainJWT page",
                "consumes": [
                    "application/json"
                ],
                "produces": [
                    "application/json"
                ],
                "summary": "MainJWT",
                "responses": {
                    "200": {
                        "description": "OK",
                        "schema": {
                            "type": "string"
                        }
                    }
                }
            }
        },
        "/login": {
            "get": {
                "description": "Login by basic auth",
                "consumes": [
                    "application/json"
                ],
                "produces": [
                    "application/json"
                ],
                "summary": "Login",
                "parameters": [
                    {
                        "type": "string",
                        "description": "Username",
                        "name": "username",
                        "in": "query",
                        "required": true
                    },
                    {
                        "type": "string",
                        "description": "Password",
                        "name": "password",
                        "in": "query",
                        "required": true
                    }
                ],
                "responses": {
                    "200": {
                        "description": "OK",
                        "schema": {
                            "$ref": "#/definitions/handlers.LoginStruct"
                        }
                    },
                    "401": {
                        "description": "Unauthorized",
                        "schema": {
                            "$ref": "#/definitions/errors.ApiError"
                        }
                    },
                    "500": {
                        "description": "Internal Server Error",
                        "schema": {
                            "$ref": "#/definitions/errors.ApiError"
                        }
                    }
                }
            }
        }
    },
    "definitions": {
        "errors.ApiError": {
            "type": "object",
            "properties": {
                "error": {
                    "type": "string"
                },
                "message": {
                    "type": "string"
                },
                "status": {
                    "type": "integer"
                }
            }
        },
        "handlers.Cat": {
            "type": "object",
            "properties": {
                "name": {
                    "type": "string"
                },
                "type": {
                    "type": "string"
                }
            }
        },
        "handlers.Dog": {
            "type": "object",
            "properties": {
                "name": {
                    "type": "string"
                },
                "type": {
                    "type": "string"
                }
            }
        },
        "handlers.Hamster": {
            "type": "object",
            "properties": {
                "name": {
                    "type": "string"
                },
                "type": {
                    "type": "string"
                }
            }
        },
        "handlers.LoginStruct": {
            "type": "object",
            "properties": {
                "message": {
                    "type": "string"
                },
                "token": {
                    "type": "string"
                }
            }
        }
    }
}